team_divide/__init__.py
team_divide/div.py
team_divide-0.1.3.dist-info/METADATA
team_divide-0.1.3.dist-info/WHEEL
team_divide-0.1.3.dist-info/entry_points.txt
team_divide-0.1.3.dist-info/top_level.txt
team_divide-0.1.3.dist-info/RECORD
