Metadata-Version: 2.1
Name: team_divide
Version: 0.1.3
Summary: Default template for PDM package
Author-email: Kimwonjoon <kimpass189@gmail.com>
License: MIT
Requires-Python: >=3.9
